<?xml version="1.0" encoding="utf-8"?>
<cms.contentitem>
  <ContentItemContentFolderID>
    <CodeName>Root</CodeName>
    <GUID>9d6509a4-a231-4837-8f1c-81a90705f988</GUID>
    <ObjectType>cms.contentfolder</ObjectType>
  </ContentItemContentFolderID>
  <ContentItemContentTypeID>
    <CodeName>KwFeeds.SingleProduct</CodeName>
    <GUID>23afb3ea-3a83-4231-acfb-1987c2875a67</GUID>
    <ObjectType>cms.contenttype</ObjectType>
  </ContentItemContentTypeID>
  <ContentItemGUID>39e076eb-1248-48cc-a125-cd0024d674b3</ContentItemGUID>
  <ContentItemIsReusable>True</ContentItemIsReusable>
  <ContentItemIsSecured>False</ContentItemIsSecured>
  <ContentItemName>Product-0fme0twn</ContentItemName>
</cms.contentitem>