<?xml version="1.0" encoding="utf-8"?>
<cms.contenttype>
  <ClassContentTypeType>Website</ClassContentTypeType>
  <ClassDisplayName>ContactPage</ClassDisplayName>
  <ClassFormDefinition>
    <form>
      <field column="ContentItemDataID" columntype="integer" enabled="true" guid="101c489f-d304-46a7-93eb-35785a2e2b7a" isPK="true" />
      <field column="ContentItemDataCommonDataID" columntype="integer" enabled="true" guid="21ff789e-732f-45e1-8b41-9bbaff1d5e15" refobjtype="cms.contentitemcommondata" reftype="Required" system="true" />
      <field column="ContentItemDataGUID" columntype="guid" enabled="true" guid="839223e8-8dd1-4a4f-b836-d7c400495ccd" isunique="true" system="true" />
      <field column="LocationName" columnprecision="0" columnsize="200" columntype="text" enabled="true" guid="33b84cee-062c-4564-bbb0-a6095ad5d54d" visible="true">
        <properties>
          <explanationtextashtml>False</explanationtextashtml>
          <fieldcaption>LocationName</fieldcaption>
          <fielddescriptionashtml>False</fielddescriptionashtml>
        </properties>
        <settings>
          <controlname>Kentico.Administration.TextInput</controlname>
        </settings>
      </field>
      <field column="Title" columnprecision="0" columnsize="200" columntype="text" enabled="true" guid="8b572ceb-2af5-41b0-9b73-31610eed034e" visible="true">
        <properties>
          <explanationtextashtml>False</explanationtextashtml>
          <fieldcaption>Title</fieldcaption>
          <fielddescriptionashtml>False</fielddescriptionashtml>
        </properties>
        <settings>
          <controlname>Kentico.Administration.TextInput</controlname>
        </settings>
      </field>
      <field allowempty="true" column="Image" columnprecision="0" columntype="contentitemreference" enabled="true" guid="57fa654e-b8f9-4702-9e1e-4b7cef87faeb" visible="true">
        <properties>
          <explanationtextashtml>False</explanationtextashtml>
          <fieldcaption>Image</fieldcaption>
          <fielddescriptionashtml>False</fielddescriptionashtml>
        </properties>
        <settings>
          <AllowedContentItemTypeIdentifiers>
            <![CDATA[["fd1947a4-e04b-441b-a76c-1ed826fb766e"]]]>
          </AllowedContentItemTypeIdentifiers>
          <controlname>Kentico.Administration.ContentItemSelector</controlname>
          <MaximumItems>1</MaximumItems>
          <MinimumItems>1</MinimumItems>
          <SelectionType>contentTypes</SelectionType>
        </settings>
      </field>
      <field column="About" columnprecision="0" columntype="longtext" enabled="true" guid="44dc5719-49b6-4833-abc2-4a3098917fb2" visible="true">
        <properties>
          <explanationtextashtml>False</explanationtextashtml>
          <fieldcaption>About</fieldcaption>
          <fielddescriptionashtml>False</fielddescriptionashtml>
        </properties>
        <settings>
          <controlname>Kentico.Administration.TextArea</controlname>
          <CopyButtonVisible>False</CopyButtonVisible>
          <MaxRowsNumber>5</MaxRowsNumber>
          <MinRowsNumber>3</MinRowsNumber>
        </settings>
      </field>
      <field column="ContactName" columnprecision="0" columnsize="200" columntype="text" enabled="true" guid="5a0f736b-8bfc-4b0c-bfba-ba9b4b6c9bbc" visible="true">
        <properties>
          <explanationtextashtml>False</explanationtextashtml>
          <fieldcaption>Contact Name</fieldcaption>
          <fielddescriptionashtml>False</fielddescriptionashtml>
        </properties>
        <settings>
          <controlname>Kentico.Administration.TextInput</controlname>
        </settings>
      </field>
      <field column="Address" columnprecision="0" columntype="longtext" enabled="true" guid="3cbccfb1-fbfe-4761-8b74-cd3e0eb790ba" visible="true">
        <properties>
          <explanationtextashtml>False</explanationtextashtml>
          <fieldcaption>Address</fieldcaption>
          <fielddescriptionashtml>False</fielddescriptionashtml>
        </properties>
        <settings>
          <controlname>Kentico.Administration.TextArea</controlname>
          <CopyButtonVisible>False</CopyButtonVisible>
          <MaxRowsNumber>5</MaxRowsNumber>
          <MinRowsNumber>3</MinRowsNumber>
        </settings>
      </field>
      <field column="Phone" columnprecision="0" columnsize="200" columntype="text" enabled="true" guid="c5528604-b2af-42df-80d5-17ba1f2ad5a9" visible="true">
        <properties>
          <explanationtextashtml>False</explanationtextashtml>
          <fieldcaption>Phone</fieldcaption>
          <fielddescriptionashtml>False</fielddescriptionashtml>
        </properties>
        <settings>
          <controlname>Kentico.Administration.TextInput</controlname>
        </settings>
      </field>
    </form>
  </ClassFormDefinition>
  <ClassGUID>45d32504-a888-4436-9ec9-812176d1a910</ClassGUID>
  <ClassHasUnmanagedDbSchema>False</ClassHasUnmanagedDbSchema>
  <ClassIconClass>xp-smartphone</ClassIconClass>
  <ClassName>DancingGoat.ContactPage</ClassName>
  <ClassTableName>DancingGoat_ContactPage</ClassTableName>
  <ClassType>Content</ClassType>
  <ClassWebPageHasUrl>False</ClassWebPageHasUrl>
</cms.contenttype>